sinj/CircularDependencyError.py
sinj/Container.py
sinj/DependencyConflictError.py
sinj/DependencyNotFoundError.py
sinj/DependencyNotMappedError.py
sinj/TypeValidator.py
sinj/TypeValidatorError.py
sinj/__init__.py
sinj-0.4.1.dist-info/LICENSE.txt
sinj-0.4.1.dist-info/METADATA
sinj-0.4.1.dist-info/WHEEL
sinj-0.4.1.dist-info/top_level.txt
sinj-0.4.1.dist-info/RECORD
