Metadata-Version: 2.1
Name: sinj
Version: 0.4.1
Summary: IoC container
Author-email: Marius Kavaliauskas <mariuskava+sinj@gmail.com>
License: MIT License
Project-URL: Homepage, https://gitlab.com/mrsk/sinj
Project-URL: Issue Tracker, https://gitlab.com/mrsk/sinj/-/issues
Project-URL: Source Code, https://gitlab.com/mrsk/sinj
Keywords: ioc,inverse-of-control,injection,dependency-injection,dependencies-container
Classifier: Programming Language :: Python :: 3
Classifier: License :: OSI Approved :: MIT License
Classifier: Topic :: Software Development :: Libraries
Classifier: Topic :: Software Development :: Libraries :: Python Modules
Requires-Python: >=3.7
License-File: LICENSE.txt
